azure/mgmt/privatedns/__init__.py
azure/mgmt/privatedns/_configuration.py
azure/mgmt/privatedns/_patch.py
azure/mgmt/privatedns/_private_dns_management_client.py
azure/mgmt/privatedns/_serialization.py
azure/mgmt/privatedns/_vendor.py
azure/mgmt/privatedns/_version.py
azure/mgmt/privatedns/py.typed
azure/mgmt/privatedns/aio/__init__.py
azure/mgmt/privatedns/aio/_configuration.py
azure/mgmt/privatedns/aio/_patch.py
azure/mgmt/privatedns/aio/_private_dns_management_client.py
azure/mgmt/privatedns/aio/operations/__init__.py
azure/mgmt/privatedns/aio/operations/_patch.py
azure/mgmt/privatedns/aio/operations/_private_zones_operations.py
azure/mgmt/privatedns/aio/operations/_record_sets_operations.py
azure/mgmt/privatedns/aio/operations/_virtual_network_links_operations.py
azure/mgmt/privatedns/models/__init__.py
azure/mgmt/privatedns/models/_models_py3.py
azure/mgmt/privatedns/models/_patch.py
azure/mgmt/privatedns/models/_private_dns_management_client_enums.py
azure/mgmt/privatedns/operations/__init__.py
azure/mgmt/privatedns/operations/_patch.py
azure/mgmt/privatedns/operations/_private_zones_operations.py
azure/mgmt/privatedns/operations/_record_sets_operations.py
azure/mgmt/privatedns/operations/_virtual_network_links_operations.py
azure_mgmt_privatedns-1.1.0.dist-info/LICENSE
azure_mgmt_privatedns-1.1.0.dist-info/METADATA
azure_mgmt_privatedns-1.1.0.dist-info/WHEEL
azure_mgmt_privatedns-1.1.0.dist-info/top_level.txt
azure_mgmt_privatedns-1.1.0.dist-info/RECORD
